LICENSE
README.md
setup.py
crystine/__init__.py
crystine/galign.py
crystine/ginfo.py
crystine/gmass.py
crystine/operations.py
crystine/swap1.py
crystine/swap2.py
crystine.egg-info/PKG-INFO
crystine.egg-info/SOURCES.txt
crystine.egg-info/dependency_links.txt
crystine.egg-info/entry_points.txt
crystine.egg-info/requires.txt
crystine.egg-info/top_level.txt