Metadata-Version: 2.1
Name: crystine
Version: 0.3.1
Summary: A data analysis library for computational chemistry
Home-page: UNKNOWN
Author: Anand
Author-email: anandsr724@gmail.com
License: UNKNOWN
Platform: UNKNOWN
Requires-Python: >=3.6
License-File: LICENSE
